Workbook
Name aporte: App!$D$17
Name patrimonio: App!$D$20
Name qtd_anos: App!$D$18
Name rendimento_carteira: App!$D$13
Name taxa_mensal: App!$D$19

Sheet App
B11: Configurações
B12: Salário | D12: 3000
B13: Rendimento Carteira | D13: 0.006
B14: Sugestão de Investimento (30%) | D14: =D12*30% -> 900
B16: Investimento Mensal
B17: Quanto investir por mês ? | D17: 400
A18: 2 | B18: Por quantos anos ? | D18: 4
A19: 5 | B19: Taxa de rendimento mensal ? | D19: 0.01079
A20: 10 | B20: Patrimônio acumulado ? | D20: =FV(taxa_mensal,qtd_anos*12,aporte*-1) -> 24981.741
A21: 20 | B21: Dividendos mensais ? | D21: =patrimonio*rendimento_carteira -> 149.89045
A22: 30
B23: Cenários | D23: Dividendo
A24: 2 | B24: Quanto em 2 Anos ? | C24: =FV($D$19,$A24*12,$D$17*-1) -> 10891.051 | D24: =C24*rendimento_carteira -> 65.346306
A25: 5 | B25: Quanto em 5 Anos ? | C25: =FV($D$19,$A25*12,$D$17*-1) -> 33510.766 | D25: =C25*rendimento_carteira -> 201.06459
A26: 10 | B26: Quanto em 10 Anos ? | C26: =FV($D$19,$A26*12,$D$17*-1) -> 97313.685 | D26: =C26*rendimento_carteira -> 583.88211
A27: 20 | B27: Quanto em 20 Anos ? | C27: =FV($D$19,$A27*12,$D$17*-1) -> 450079.36 | D27: =C27*rendimento_carteira -> 2700.4762
A28: 30 | B28: Quanto em 30 Anos ? | C28: =FV($D$19,$A28*12,$D$17*-1) -> 1728867.9 | D28: =C28*rendimento_carteira -> 10373.207
B30: PERFIL | C30: Moderado
B31: VALOR A SER INVESTIDO POR MÊS | C31: =aporte -> 400
B33: Tipo de FII | C33: Percentual Sugerido | D33: Valores
B34: PAPEL | C34: =VLOOKUP($C$30&"-"&B34,Perfil!$B:$E,4,FALSE) -> 0.3 | D34: =C34*$C$31 -> 120
B35: TIJOLO | C35: =VLOOKUP($C$30&"-"&B35,Perfil!$B:$E,4,FALSE) -> 0.35 | D35: =C35*$C$31 -> 140
B36: HÍBRIDOS | C36: =VLOOKUP($C$30&"-"&B36,Perfil!$B:$E,4,FALSE) -> 0.1 | D36: =C36*$C$31 -> 40
B37: FOFs | C37: =VLOOKUP($C$30&"-"&B37,Perfil!$B:$E,4,FALSE) -> 0.1 | D37: =C37*$C$31 -> 40
B38: DESENVOLVIMENTO | C38: =VLOOKUP($C$30&"-"&B38,Perfil!$B:$E,4,FALSE) -> 0.1 | D38: =C38*$C$31 -> 40
B39: HOTELARIAS | C39: =VLOOKUP($C$30&"-"&B39,Perfil!$B:$E,4,FALSE) -> 0.05 | D39: =C39*$C$31 -> 20
D40: =SUM(D34:D39) -> 400

Sheet Perfil
B3: CHAVE | C3: PERFIL | D3: TIPO DE FII | E3: %
B4: =C4&"-"&D4 -> Conservador-PAPEL | C4: Conservador | D4: PAPEL | E4: 0.35 | G4: Tipo | H4: Taxa %
B5: =C5&"-"&D5 -> Conservador-TIJOLO | C5: Conservador | D5: TIJOLO | E5: 0.45 | G5: Conservador-TIJOLO | H5: =VLOOKUP(G5,$B:$E,4,FALSE) -> 0.45
B6: =C6&"-"&D6 -> Conservador-HÍBRIDOS | C6: Conservador | D6: HÍBRIDOS | E6: 0.1
B7: =C7&"-"&D7 -> Conservador-FOFs | C7: Conservador | D7: FOFs | E7: 0.05
B8: =C8&"-"&D8 -> Conservador-DESENVOLVIMENTO | C8: Conservador | D8: DESENVOLVIMENTO | E8: 0
B9: =C9&"-"&D9 -> Conservador-HOTELARIAS | C9: Conservador | D9: HOTELARIAS | E9: 0.05
B10: =C10&"-"&D10 -> Moderado-PAPEL | C10: Moderado | D10: PAPEL | E10: 0.3
B11: =C11&"-"&D11 -> Moderado-TIJOLO | C11: Moderado | D11: TIJOLO | E11: 0.35
B12: =C12&"-"&D12 -> Moderado-HÍBRIDOS | C12: Moderado | D12: HÍBRIDOS | E12: 0.1
B13: =C13&"-"&D13 -> Moderado-FOFs | C13: Moderado | D13: FOFs | E13: 0.1
B14: =C14&"-"&D14 -> Moderado-DESENVOLVIMENTO | C14: Moderado | D14: DESENVOLVIMENTO | E14: 0.1
B15: =C15&"-"&D15 -> Moderado-HOTELARIAS | C15: Moderado | D15: HOTELARIAS | E15: 0.05
B16: =C16&"-"&D16 -> Agressivo-PAPEL | C16: Agressivo | D16: PAPEL | E16: 0.2
B17: =C17&"-"&D17 -> Agressivo-TIJOLO | C17: Agressivo | D17: TIJOLO | E17: 0.3
... B21: =C21&"-"&D21 -> Agressivo-HOTELARIAS | C21: Agressivo | D21: HOTELARIAS | E21: 0.1
